arxiv_bot/__init__.py
arxiv_bot/knowledge_base/__init__.py
arxiv_bot/knowledge_base/constructors.py
arxiv_bot/knowledge_base/database.py
arxiv_bot/manager/__init__.py
arxiv_bot/manager/bots.py
arxiv_bot/templates.py
arxiv_bot-0.0.6.dist-info/WHEEL
arxiv_bot-0.0.6.dist-info/METADATA
arxiv_bot-0.0.6.dist-info/RECORD
